auth/__init__.py
auth/__main__.py
mfa_auth-0.1.2.dist-info/METADATA
mfa_auth-0.1.2.dist-info/WHEEL
mfa_auth-0.1.2.dist-info/entry_points.txt
mfa_auth-0.1.2.dist-info/top_level.txt
mfa_auth-0.1.2.dist-info/RECORD
